MrCrop/MrCrop.py
MrCrop/__init__.py
MrCrop/__version__.py
MrCrop/constants.py
MrCrop-1.0.0.dist-info/LICENSE
MrCrop-1.0.0.dist-info/LICENSE-3RD-PARTY.txt
MrCrop-1.0.0.dist-info/METADATA
MrCrop-1.0.0.dist-info/WHEEL
MrCrop-1.0.0.dist-info/entry_points.txt
MrCrop-1.0.0.dist-info/top_level.txt
MrCrop-1.0.0.dist-info/RECORD
